## 数据类型

### 基本数据类型（Primitive Data Types）

#### 1. 八种类型

| 类型名称  | 类型定义           | 类型取值                                                     |
| --------- | ------------------ | ------------------------------------------------------------ |
| *boolean* | 布尔值，作二元判断 | 占用大小未定 *true*, *false*                                 |
| *byte*    | 8位有符号整数      | 最小值-128，最大值127                                        |
| *short*   | 16位有符号整数     | 最小值-32768，最大值32767                                    |
| *int*     | 32位有符号整数     | 最小值-2147483648（-231），最大值2147483647（231-1）         |
| *long*    | 64位有符号整数     | -263~(263-1)                                                 |
| *float*   | 32位浮点数         | 1.4E-45~3.4028235E38                                         |
| *double*  | 64位浮点数         | 4.9E-324~1.7976931348623157E308                              |
| char      | 16位Unicode字符    | 它的最小值为`'\u0000'`（或0），最大值为`'\uffff'`（或65,535，包括端值） |

PS：

1. 使用Integer类可将`int`数据类型用作无符号整数。有关更多信息，请参见“数字类”部分。像静态方法`compareUnsigned`，`divideUnsigned`等已被添加到 [`Integer`](https://docs.oracle.com/javase/8/docs/api/java/lang/Integer.html)类，以支持算术运算的无符号整数。
2. 永远不要将`float`、`double` 用于精确值，例如货币。而是使用 [java.math.BigDecimal](https://docs.oracle.com/javase/8/docs/api/java/math/BigDecimal.html)类。 [数字和字符串](https://docs.oracle.com/javase/tutorial/java/data/index.html)覆盖`BigDecimal`以及Java平台提供的其他有用的类。
3. JVM 会在编译时期将 boolean 类型的数据转换为 int，使用 1 来表示 true，0 表示 false。JVM 支持 boolean 数组，但是是通过读写 byte 数组来实现的。

#### 2. 默认值

编译器为**已声明**但**未初始化**的属性字段（成员变量）设置为默认值，但是对于局部变量则不会设置默认值

| **数据类型**         | **默认值（用于字段）** |
| -------------------- | ---------------------- |
| byte                 | 0                      |
| short                | 0                      |
| int                  | 0                      |
| long                 | 0L                     |
| float                | 0.0f                   |
| double               | 0.0d                   |
| char                 | '\ u0000'              |
| String（或任何对象） | null                   |
| boolean              | false                  |

#### 3. 字面值（Literals）

基础数据类型不用通过关键字`new` 来创建，因为它不是通过类所创建的对象。字面值是固定值得源代码的表示

1. 整数字面值

   - 一个整型如果以字母L或l结尾，则为long类型，否则为int类型

   - 数值类型`byte`，`short`，`int`，并且`long`类型的直面值都可以用指针书表示
   - 16进制数以前缀 `0x`开头 `int hexVal = 0x1a;`
   - 2进制数以前缀 `0b`开头 `int binVal = 0b11010;`

2. 浮点型常量

   - 单精度以 `F/f`结尾
   - 双精度以 `D/d`结尾

3. 字符和字符串

   - 文本的类型 `字符 `和 `字符串 `可包含任何Unicode (utf-16)字符

4. 类型字面值

   - 例如：`String.class` 代表类型本身

#### 4. 数据类型转换

- 隐式转换
- 强制转换

##### 隐式转换

发生隐式转换的条件：

1. 由小范围类型 --> 大范围类型
   转换可以自动发生，因为没有精度丢失。反过来由大范围类型 转成 小范围类型，可能会存在数据丢失

   >表数范围大小：(byte，short，char) < int < long < float < double

2. 类的向上转型
   父类的引用指向子类的对象

3. 整型数值类型 与 浮点型进行计算后，结果会转为浮点类型

   > 可见 long 虽然精度大于 float 类型，但是结果为浮点数类型

   ```java
   long x = 30;
   float y = 14.3f;
   System.out.println("x/y = " + x/y);
   
   //sout
   x/y = 1.9607843
   ```

##### 强制转换

使用 (+类型) 手动强制类型转换

```java
float f = 25.5f;
int x = (int)f;
System.out.println("x = " + x);

// 引用类型 也可以强转
String xx = (String) ob ject
```

##### 包装类的拆装箱操作

从JDK5开始，引入了自动装箱的特性

思考点：（主要是查看包装类的ValueOf方法，看看拆箱的实际操作步骤）

1. 包装类中的缓存池大小分别为：

   - boolean values true and false

   - all byte values

   - short values between -128 and 127

   - int values between -128 and 127

     > Integer 的缓冲池 IntegerCache 很特殊，这个缓冲池的下界是 - 128，上界默认是 127，但是这个上界是可调的，在启动 jvm 的时候，通过 -XX:AutoBoxCacheMax=<size> 来指定这个缓冲池的大小，该选项在 JVM 初始化的时候会设定一个名为 java.lang.IntegerCache.high 系统属性，然后 IntegerCache 初始化的时候就会读取该系统属性来决定上界。

   - char in the range \u0000 to \u007F

   实例：

   ```java
   public class Main {
       public static void main(String[] args) {
            
           Integer i1 = 100;
           Integer i2 = 100;
           Integer i3 = 200;
           Integer i4 = 200;
            
           System.out.println(i1==i2);
           System.out.println(i3==i4);
       }
   }
   
   //输出...
   true
   false
   
   //缓存代码
   public static Integer valueOf(int i) {
           if(i >= -128 && i <= IntegerCache.high)
               return IntegerCache.cache[i + 128];
           else
               return new Integer(i);
       }
   
   ```

   **注意**：Integer、Short、Byte、Character、Long这几个类的valueOf方法的实现是类似的；Double、Float的valueOf方法的实现是类似的（浮点数没有缓存数值）

2. 思考``Integer i = new Integer(xxx)``和``Integer i =xxx;``这两种方式的区别

   >第一种不触发自动装箱，第二种触发自动装箱
   >
   >第二种方式的执行效率和资源占用在一般性情况下要优于第一种情况（注意这并不是绝对的）

3. 自动装箱时，`equals`与``==``

   >当 "=="运算符的两个操作数其中有一个操作数是表达式（即包含算术运算）则比较的是数值（即会触发自动拆箱的过程）
   >
   >主要由于 算数运算符导致的 拆装箱操作

   ```java
   public static void main(String[] args) {
           Integer a = 1;
           Integer b = 2;
           Integer c = 3;
           Integer d = 3;
           Integer e = 321;
           Integer f = 321;
   
           Long g = 3L;
           Long h = 2L;
           Long I = 642L;
           Long J = 1L;
   
           // 范围A : -128 ~ 127
           System.out.println(c==d);           // 在范围A，属于同一个引用，比较地址
           System.out.println(e==f);           // 不在范围A，不属于同一个引用，比较地址
           System.out.println(c==(a+b));       // a + b ->拆箱，c也拆箱，比较数值
           System.out.println(c.equals(a+b));  // a + b ->拆箱，c还是对象，a+b的结果装箱成Integer，与c的类型 + 数值一起比较
           System.out.println(g==(a+b));       // a + b ->拆箱，g也拆箱，比较数值
           System.out.println(I==(e+f));       // e + f ->拆箱，i也拆箱，比较数值
           System.out.println(I.equals(e+f));  // e + f ->拆箱，e + f的结果装箱成Integer，I的类型是Long，与Integer类型不符
           System.out.println(g.equals(a+b));  // a + b ->拆箱，e + f的结果装箱成Integer，g的类型是Long，与Integer类型不符
           System.out.println(g.equals(a+h));  // a + h ->拆箱（变成long型数字）, a + h的结果装箱成Long，g的类型是Long，类型 + 数值一起比较相等
           System.out.println(c==(h+J));       // h + j的结果是一个数值，所以c拆箱，比较数值
       }
   ```

   从另一个角度说明：

   > 基础数据类型的比较操作使用 `==`，包装类（引用类型）的比较操作使用 `equals` 方法

### 引用数据类型

#### 1. 数组

##### 数组也是类

java中数组是对象，父类是Object

但是java中，没有**类文件**与数组对应，数组是运行时jvm动态生成的。

```java
char[] c={'a','b','c'}; 

System.out.println(c instanceof char[]); 
System.out.println(c instanceof Object); 
System.out.println(c.getClass().getName()); System.out.println(c.getClass().getSuperclass().getName()); 

//Output: 
//true 
//true 
//[C 
//java.lang.Object
```

##### 数组的length

- java语言规范中写道:

    >Every array has an associated Class object, shared with all other arrays with the same component type.
    >
    >Although an array type is not a class, the Class object of every array acts as if:
    >
    >- The direct superclass of every array type is Object. **//继承自Object**
    >- Every array type implements the interfaces Cloneable and java.io.Serializable. **//实现了两接口**

- 在jvm中的heap中存储对象实例的那块内存有一部分——对象头，其中包含着数组对象的``_length``值

- 从Java语言到Class文件，Java源码编译器会识别出对数组类型的length字段的访问，并生成对应的字节码

  ```java
                  base.load();
                  if (sym == syms.lengthVar) {
                      code.emitop0(arraylength);// 指令 arrylength 获取数组长度
                      result = items.makeStackItem(syms.intType);
                  }
  ```

  关于``arraylength``java语言规范中写道：

  >All arrays have associated lengths, which are accessed via the *arraylength* instruction.

  ``arraylength`` 指令的描述：

  ```markdown
  arraylength
  Operation
  	Get length of array
  
  Forms
  	arraylength = 190 (0xbe)
  
  Operand Stack
  ..., arrayref →
  
  ..., length
  
  Description
      The arrayref must be of type reference and must refer to an array. It is popped from the operand stack. The length of the array it references is determined. That length is pushed onto the operand stack as an int.
  
  Run-time Exceptions
      If the arrayref is null, the arraylength instruction throws a NullPointerException.
  ```

- 具体JVM虚拟机的具体实现

    >以HotSpot VM为例，答案是在数组对象的对象头里有一个_length字段，记录数组长度。arraylength字节码的实现只要去读那个 _length字段即可。

##### 深入理解

- **问答-数组类型为什么特殊：**

  >可是为什么要把数组特殊设计呢？

  因为Java里只有数组是**可变长度**的对象——类型相同的对象的大小可以不同。
  例如说java.lang.Integer，看到类型就知道这个对象有多大了；而int[]，由于length不是长度的一部分，看到int[]并不能知道对象有多大，而必须额外在每个数组实例都带上length信息。

- 数组类型的强转
  Object[] 是一个运行时存在的类型 --> 父类是Object，String[] 这又是运行时存在的另一个类型，父类也是Object数组是一个整体，**数组的类型**与数组中**存的数据的类型**要区分开

  ```java
          // 报错：[Ljava.lang.Object; cannot be cast to [Ljava.lang.String;
  		Object[] os = new Object[]{"ss", "ss"};
          String[] ss = (String[]) os;
  
          // 不报错
          Object[] os1 = new String[]{"hello", "world"};
          String[] ss1 =(String[])os1;
  		
  		// 不报错
          Object o = new String[]{"hello", "world"};
          String[] ss2 =(String[])o;
  ```

#### 2. 抽象类

> 接口和抽象类提供了一种将接口（声明？）与实现分离的更加结构化的方法

- 通用接口建立了一个基本形式，以此表达所有派生类的共同部分（提供一种描述这种关系的机制）

- 抽象基类的对象几乎没有意义，限定——抽象类**不能实例化**

- 定义：包含抽象方法的类叫做*抽象类*

  > 抽象类的子类若不实现所有的抽象方法，任然是抽象类
  >
  > 不包含任何抽象方法的类也能声明为**abstract** 
  > （场景：某个类已经定义好后，发现实例化出来的对象满足不了要求，又不能改变其中的方法体。于是继承它并重写了他的子类以满足要求。于是把它定义改为抽象类，此时就出现了没有抽象方法的抽象类）

- **private abstract** 被禁止了是有意义的，因为你不可能在 **AbstractAccess** 的任何子类中合法地定义它。
- 抽象类中的方法的访问权限可以自由规定，但是接口中只能是**public**

#### 3. 接口

> java8之前，接口只能有抽象方法，可以看成是一个完全抽象的类，不包含任何方法的实现
>
> 从 Java 8 开始，接口可以拥有默认的方法实现，因为不支持默认方法的接口的维护成本太高了。在 Java 8 之前，当在接口中添加新的方法，就要修改所有实现了该接口的类

- 接口方法默认都是 public 的，并且不允许定义为 private 或者 protected

- 接口字段默认都是 static 和 final 的（so接口就成为了创建一组常量的方便的工具）

- 默认方法（java8），使用关键字**default** 

  ```java
  // interfaces/InterfaceWithDefault.java
  interface InterfaceWithDefault {
      void firstMethod();
      void secondMethod();
  
      default void newMethod() {
          System.out.println("newMethod");
      }
  }
  ```

- 静态方法（java8）
  Java 8 允许在接口中添加静态方法。这么做能恰当地把工具功能置于接口中，从而操作接口，或者成为通用的工具：

  ```java
  public interface Operations {
      void execute();
  
      static void runOps(Operations... ops) {
          for (Operations op: ops) {
              op.execute();
          }
      }
  
      static void show(String msg) {
          System.out.println(msg);
      }
  }
  ```

##### 比较抽象类与接口

- 使用场景
  - 接口的典型使用是代表一个类的类型或一个形容词，如 Runnable 或 Serializable
  - 抽象类通常是**类层次结构**的一部分或一件事物的类型，如 String 或 ActionHero
- 设计层面，描述的关系
  - 抽象类提供了一种 IS-A 关系，那么就必须满足里式替换原则，即子类对象必须能够替换掉所有父类对象
  - 接口更像是一种 LIKE-A 关系，它只是提供一种方法实现契约，并不要求接口和实现接口的类具有 IS-A 关系
- 访问权限
  - 接口的成员只能是 public（隐试）的
  - 抽象类的成员可以是 **protected** 或友元
- 构造方法
  - 接口没有构造方法
  - 抽象类可以有构造方法
- 默认方法和抽象方法
  - 接口不需要在子类中实现默认方法。默认方法可以引用其他接口的方法
  - 抽象类必须在子类中实现抽象方法
- 成员变量
  - 接口不能包含属性（除了静态属性，不支持对象状态）
  - 抽象类可以包含属性，非抽象方法可能引用这些属性
- 描述继承关系
  - 接口可以实现多个
  - 抽象类只能继承一个
- 优先使用接口而非抽象类，接口有更好的复用性

#### 4. 类

#### 5. 理解内部类

- 内部类的作用？

  - 每个内部类都能独立的继承一个接口的实现，所以无论外部类是否已经继承了某个(接口的)实现，对于内部类都没有影响。内部类使得**多继承**的解决方案变得完整（栗子如下：）

    ```java
    class WithInner {
        class Inner{
             
        }
    }
    class InheritInner extends WithInner.Inner {
          
        // InheritInner() 是不能通过编译的，一定要加上形参
        InheritInner(WithInner wi) {
            wi.super(); //必须有这句调用
        }
      
        public static void main(String[] args) {
            WithInner wi = new WithInner();
            InheritInner obj = new InheritInner(wi);
        }
    }
    ```

  - 方便将存在一定逻辑关系的类组织在一起，又可以对外界隐藏

- 成员内部类**可以无条件访问外部类的成员？

  > 会，编译器在进行编译的时候，会将成员内部类**单独**编译成一个字节码文件，``Outter.java``的代码实例如下：

  ```java
  public class Outter {
      private Inner inner = null;
      public Outter() {  
      } 
      public Inner getInnerInstance() {
          if(inner == null)
              inner = new Inner();
          return inner;
      } 
      protected class Inner {
          public Inner() {    
          }
      }
  }
  ```

  编译后：``Outter$inner.class`` 和 ``Outter.class``
  **反编译** ``Outter$inner.class``：

  ```java
  E:\Workspace\Test\bin\com\cxh\test2>javap -v Outter$Inner
  Compiled from "Outter.java"
  public class com.cxh.test2.Outter$Inner extends java.lang.Object
    SourceFile: "Outter.java"
    InnerClass:
     #24= #1 of #22; //Inner=class com/cxh/test2/Outter$Inner of class com/cxh/tes
  t2/Outter
    minor version: 0
    major version: 50
    Constant pool:
  const #1 = class        #2;     //  com/cxh/test2/Outter$Inner
  const #2 = Asciz        com/cxh/test2/Outter$Inner;
  const #3 = class        #4;     //  java/lang/Object
  const #4 = Asciz        java/lang/Object;
  const #5 = Asciz        this$0;
  const #6 = Asciz        Lcom/cxh/test2/Outter;;
  const #7 = Asciz        <init>;
  const #8 = Asciz        (Lcom/cxh/test2/Outter;)V;
  const #9 = Asciz        Code;
  const #10 = Field       #1.#11; //  com/cxh/test2/Outter$Inner.this$0:Lcom/cxh/t
  est2/Outter;
  const #11 = NameAndType #5:#6;//  this$0:Lcom/cxh/test2/Outter;
  const #12 = Method      #3.#13; //  java/lang/Object."<init>":()V
  const #13 = NameAndType #7:#14;//  "<init>":()V
  const #14 = Asciz       ()V;
  const #15 = Asciz       LineNumberTable;
  const #16 = Asciz       LocalVariableTable;
  const #17 = Asciz       this;
  const #18 = Asciz       Lcom/cxh/test2/Outter$Inner;;
  const #19 = Asciz       SourceFile;
  const #20 = Asciz       Outter.java;
  const #21 = Asciz       InnerClasses;
  const #22 = class       #23;    //  com/cxh/test2/Outter
  const #23 = Asciz       com/cxh/test2/Outter;
  const #24 = Asciz       Inner;
   
  {
  final com.cxh.test2.Outter this$0;
   
  public com.cxh.test2.Outter$Inner(com.cxh.test2.Outter);
    Code:
     Stack=2, Locals=2, Args_size=2
     0:   aload_0
     1:   aload_1
     2:   putfield        #10; //Field this$0:Lcom/cxh/test2/Outter;
     5:   aload_0
     6:   invokespecial   #12; //Method java/lang/Object."<init>":()V
     9:   return
    LineNumberTable:
     line 16: 0
     line 18: 9
   
    LocalVariableTable:
     Start  Length  Slot  Name   Signature
     0      10      0    this       Lcom/cxh/test2/Outter$Inner;
   
   
  }
  ```

  - line38：``final com.cxh.test2.Outter this$0;`` 

    > 成员内部类中保存了一个外部类的引用 ``this$0``

  - line40：``public com.cxh.test2.Outter$Inner(com.cxh.test2.Outter); `` 

    >     从这里可以看出，虽然我们在定义的内部类的构造器是无参构造器，编译器还是会默认添加一个参数，该参数的类型为指向外部类对象的一个引用，所以成员内部类中的``Outter this&0`` 指针便指向了外部类对象，因此可以在成员内部类中随意访问外部类的成员。
    >
    >     从这里也间接说明了成员内部类是依赖于外部类的，如果没有创建外部类mai的对象，则无法对``Outter this&0``引用进行初始化赋值，也就无法创建成员内部类的对象了。

- 为什么局部内部类和匿名内部类只能访问局部final变量

  > 从``JDK 1.8``开始，会默认给这两种内部类访问的field 加上final(隐式地)，所以你可能会在编译器中看到可以访问没有加final的变量，只有你去修改它时，编译器才会报错

  >如下代码，当test()方法执行完成后，变量 a 的生命周期就结束了，但是new出来的内部类Thread对象的生命周期很**可能还没有结束**，所以避免访问不到a 的情况，Java 采用了 **复制**的手段

  ```java
  public class Test {
      public static void main(String[] args)  {
           
      }
      public void test(final int b) {
          // 成员变量
          final int a = 10;
          new Thread(){
              public void run() {
                  System.out.println(a);
                  System.out.println(b);
              };
          }.start();
      }
  }
  
  // 编译后
  Compiled from "Test.java"
  class com.corejava.basejdk.Test$1 extends java.lang.Thread {
    final int val$b;
  
    final com.corejava.basejdk.Test this$0;
  
    com.corejava.basejdk.Test$1(com.corejava.basejdk.Test, int);
      Code:
         0: aload_0
         1: aload_1
         2: putfield      #1                  // Field this$0:Lcom/corejava/basejdk/Test;
         5: aload_0
         6: iload_2
         7: putfield      #2                  // Field val$b:I
        10: aload_0
        11: invokespecial #3                  // Method java/lang/Thread."<init>":()V
        14: return
  
    public void run();
      Code:
         0: getstatic     #4                  // Field java/lang/System.out:Ljava/io/PrintStream;
         3: bipush        10
         5: invokevirtual #5                  // Method java/io/PrintStream.println:(I)V
         8: getstatic     #4                  // Field java/lang/System.out:Ljava/io/PrintStream;
        11: aload_0
        12: getfield      #2                  // Field val$b:I
        15: invokevirtual #5                  // Method java/io/PrintStream.println:(I)V
        18: return
  }
  ```

  - line20：``  final int val$b;`` 和 line24 ``com.corejava.basejdk.Test$1(com.corejava.basejdk.Test, int);``
    可以看出 对于编译时不能确认的变量b，编译器复制了一份``val$b``，将其作为构造器的参数在构造时初始化。

  - line39：``3: bipush    10``可以看出编译器将操作数10压栈，表示使用的是一个本地局部变量

    > 如果这个变量的值在编译期间可以确定，则编译器默认会在匿名内部类（局部内部类）的常量池中添加一个内容相等的字面量或直接将相应的字节码嵌入到执行字节码中
    >
    > 可以看出匿名内部类使用的变量是另一个局部变量，只不过值和方法中局部变量的值相等，因此和方法中的局部变量完全独立开

  - 可以看出，编译时进栈后，如果变量a还能被修改，就会出现不一致的问题，使用final修饰变量a就能避免a再被改变。（这是由于匿名内部类中的变量的声明周期导致）

- 为什么要将局部变量规定成final类型才允许访问，而外部类的成员变量不需要final修饰也能访问？

  - 匿名内部类访问二者的方式不同：

    - 编译器为匿名内部类添加的构造函数中传入了外部类的引用，通过这个引用可以访问到成员变量，即使该变量的值发生更改，该更改也将反映在匿名类中，因为它是相同的引用。
    - 编译器将局部变量的副本给了匿名内部类的实现。因此，在匿名类中可以使用局部变量之前，必须将其定型为最终变量，以便以后不会更改其值。

  - 生命周期的角度看：

    - 成员变量在外部类对象的生存期内存在，因此可以由内部类实例引用它
    - 局部变量只在方法调用期间存在，并且由编译器以不同的方式处理，因为它的隐式副本是作为内部类的成员生成的。在不声明局部变量final的情况下，可以更改它，这会导致一些细微的错误，因为内部类仍然引用该变量的原始值。

  - 总而言之，将变量设为final可以消除所有这些可能性--由于根本无法更改该值，因此开发者无需担心此类更改是否可见。 

    > 创建匿名内部类的实例时，该类中使用的任何变量都将通过自动生成的构造函数复制其值。 这样避免了编译器不得不自动生成各种额外的类型来保存“局部变量”的逻辑状态，例如C＃编译器确实...（当C＃在匿名函数中捕获变量时，它实际上捕获了变量- 闭包可以通过该方法的主体看到的方式来更新变量，反之亦然。）
    >
    > 由于该值已被复制到匿名内部类的实例中，因此如果变量的其余部分可以被该方法的其余部分修改，则看起来会很奇怪-您可能会发现代码似乎正在使用过期的变量（ 因为这实际上是将要发生的事情……您将使用在不同时间拍摄的副本）。 同样，如果您可以在匿名内部类中进行更改，则开发人员可能希望这些更改在封闭方法的正文中可见
    >
    > 
    >
    > 允许方法和匿名内部类看到彼此更改的唯一方法是使用某种描述的可变类型。 这可能是外部类的类本身，一个数组，一个可变的包装器类型……诸如此类。 基本上，这有点像一种方法与另一种方法之间的通信：调用者看不到对一个方法的参数所做的更改，但可以看到对参数所引用的对象所做的更改。


    
    

#### 6. 枚举类型

##### 什么是枚类型

``java5``引入特性，关键字 ``enum ``枚举类型，枚举类型对象是运行时生产的

声明如下：

```java
public abstract class Enum<E extends Enum<E>>
        implements Comparable<E>, Serializable
//每个枚举实例的名字        
private final String name;
//从0开始的序号
private final int ordinal;
```

##### 枚举类的定义

- 最简化（相当于以前的常量类）

  每个类型都会赋予：``name`` 和 ``ordinal``(按照被声明的顺序，0起始)

  ```java
  // 定义一个星期的枚举类
  public enum WeekEnum {
      // 在第一行显式地列出7个枚举实例(枚举值)，系统会自动添加 public static final 修饰
      SUNDAY, MONDAY, TUESDAY, WEDNESDAY, THURSDAY,FRIDAY,SATURDAY;
  } 
  ```

- 包含自定义成员
  构造器只能私有

  > 即使不声明为 private，我们只能在 enum 定义的内部使用其构造器创建 enum 实例。一旦 enum 的定义结束，编译器就不允许我们再使用其构造器来创建任何实例了。

  ```java
  public enum WeekEnum {
      
      //由带参数的构造器决定，必须传入对应的参数
      SUNDAY("星期日"), MONDAY("星期一"), TUESDAY("星期二"), WEDNESDAY("星期三"), 
      THURSDAY("星期四"), FRIDAY("星期五"), SATURDAY("星期六");
  
      // private 修饰的实例变量
      private String date;
  
      // 定义一个带参数的构造器，枚举类的构造器只能使用 private 修饰
      private WeekEnum(String date) {
          this.date = date;
      }
  
      // 定义 get set 方法
      public String getDate() {
          return date;
      }
  
      public void setDate(String date) {
          this.date = date;
      }
      
  }
  ```

##### 使用方法

- 使用接口（或者枚举）组织枚举，实物分类的例子

  > ``enum``无法被继承，在接口内部，创建实现该接口的枚举，以此将元素进行分组

  ```java
  package enums.menu;
  public interface Food {
      enum Appetizer implements Food {
          SALAD, SOUP, SPRING_ROLLS;
      }
      enum MainCourse implements Food {
          LASAGNE, BURRITO, PAD_THAI,
          LENTILS, HUMMOUS, VINDALOO;
      }
      enum Dessert implements Food {
          TIRAMISU, GELATO, BLACK_FOREST_CAKE,
          FRUIT, CREME_CARAMEL;
      }
      enum Coffee implements Food {
          BLACK_COFFEE, DECAF_COFFEE, ESPRESSO,
          LATTE, CAPPUCCINO, TEA, HERB_TEA;
      }
  }
  ```

  > 当类型过多时，可以``enum`` 找那个 套 ``enum``

  ```java
  public enum Course {
      APPETIZER(Food.Appetizer.class),
      MAINCOURSE(Food.MainCourse.class),
      DESSERT(Food.Dessert.class),
      COFFEE(Food.Coffee.class);
      private Food[] values;
      private Course(Class<? extends Food> kind) {
          values = kind.getEnumConstants();
      }
      public Food randomSelection() {
          return Enums.random(values);
      }
  }
  ```

- 使用 ``EnumSet`` 替代 Flags

- 使用 ``EnumMap``
